avh_api/__init__.py
avh_api/api_client.py
avh_api/configuration.py
avh_api/exceptions.py
avh_api/model_utils.py
avh_api/rest.py
avh_api/api/__init__.py
avh_api/api/arm_api.py
avh_api/apis/__init__.py
avh_api/model/__init__.py
avh_api/model/address.py
avh_api/model/agent_app.py
avh_api/model/agent_app_ready_response.py
avh_api/model/agent_app_status.py
avh_api/model/agent_apps_list.py
avh_api/model/agent_apps_status_list.py
avh_api/model/agent_error.py
avh_api/model/agent_icons.py
avh_api/model/agent_install_body.py
avh_api/model/agent_profiles_return.py
avh_api/model/agent_system_adb_auth.py
avh_api/model/agent_system_get_prop_body.py
avh_api/model/agent_value_return.py
avh_api/model/agreed_ack.py
avh_api/model/api_conflict_error.py
avh_api/model/api_error.py
avh_api/model/api_internal_consistency_error.py
avh_api/model/api_not_found_error.py
avh_api/model/api_token.py
avh_api/model/bit.py
avh_api/model/btrace_enable_options.py
avh_api/model/button.py
avh_api/model/coupon_options.py
avh_api/model/create_team.py
avh_api/model/created_by.py
avh_api/model/credentials.py
avh_api/model/domain_options.py
avh_api/model/extension.py
avh_api/model/features.py
avh_api/model/file_changes.py
avh_api/model/firmware.py
avh_api/model/gpio_state_definition.py
avh_api/model/gpios_state.py
avh_api/model/grant_trial_request_response.py
avh_api/model/hook.py
avh_api/model/image.py
avh_api/model/instance.py
avh_api/model/instance_agent_state.py
avh_api/model/instance_boot_options.py
avh_api/model/instance_boot_options_additional_tag.py
avh_api/model/instance_console_endpoint.py
avh_api/model/instance_create_options.py
avh_api/model/instance_input.py
avh_api/model/instance_netmon_state.py
avh_api/model/instance_return.py
avh_api/model/instance_services.py
avh_api/model/instance_start_options.py
avh_api/model/instance_state.py
avh_api/model/instance_stop_options.py
avh_api/model/invitation.py
avh_api/model/invite_revoke_params.py
avh_api/model/invite_revoke_params_ids.py
avh_api-1.0.5.dist-info/METADATA
avh_api-1.0.5.dist-info/WHEEL
avh_api-1.0.5.dist-info/top_level.txt
avh_api-1.0.5.dist-info/RECORD
